miru_agent_sdk/__init__.py
miru_agent_sdk/_base_client.py
miru_agent_sdk/_client.py
miru_agent_sdk/_compat.py
miru_agent_sdk/_constants.py
miru_agent_sdk/_exceptions.py
miru_agent_sdk/_files.py
miru_agent_sdk/_models.py
miru_agent_sdk/_qs.py
miru_agent_sdk/_resource.py
miru_agent_sdk/_response.py
miru_agent_sdk/_streaming.py
miru_agent_sdk/_types.py
miru_agent_sdk/_version.py
miru_agent_sdk/py.typed
miru_agent_sdk/_utils/__init__.py
miru_agent_sdk/_utils/_compat.py
miru_agent_sdk/_utils/_datetime_parse.py
miru_agent_sdk/_utils/_logs.py
miru_agent_sdk/_utils/_proxy.py
miru_agent_sdk/_utils/_reflection.py
miru_agent_sdk/_utils/_resources_proxy.py
miru_agent_sdk/_utils/_streams.py
miru_agent_sdk/_utils/_sync.py
miru_agent_sdk/_utils/_transform.py
miru_agent_sdk/_utils/_typing.py
miru_agent_sdk/_utils/_utils.py
miru_agent_sdk/lib/.keep
miru_agent_sdk/resources/__init__.py
miru_agent_sdk/resources/agent.py
miru_agent_sdk/resources/device.py
miru_agent_sdk/types/__init__.py
miru_agent_sdk/types/agent_health_response.py
miru_agent_sdk/types/agent_version_response.py
miru_agent_sdk/types/device_retrieve_response.py
miru_agent_sdk/types/device_sync_response.py
miru_agent_sdk-0.2.1.dist-info/METADATA
miru_agent_sdk-0.2.1.dist-info/WHEEL
miru_agent_sdk-0.2.1.dist-info/licenses/LICENSE
miru_agent_sdk-0.2.1.dist-info/RECORD
